asyncapi_sphinx_ext.py
asyncapi_sphinx_ext-1.0.2.dist-info/DESCRIPTION.rst
asyncapi_sphinx_ext-1.0.2.dist-info/METADATA
asyncapi_sphinx_ext-1.0.2.dist-info/RECORD
asyncapi_sphinx_ext-1.0.2.dist-info/WHEEL
asyncapi_sphinx_ext-1.0.2.dist-info/entry_points.txt
asyncapi_sphinx_ext-1.0.2.dist-info/metadata.json
asyncapi_sphinx_ext-1.0.2.dist-info/top_level.txt
