Metadata-Version: 2.0
Name: asyncapi-sphinx-ext
Version: 1.0.2
Summary: Sphinx extension for Pub/Sub Documentation
Home-page: http://github.com/mortbauer/asyncapi-sphinx-ext
Author: Martin Ortbauer
Author-email: mortbauer@gmail.com
License: MIT
Platform: UNKNOWN
Classifier: Development Status :: 4 - Beta
Classifier: Environment :: Console
Classifier: Environment :: Web Environment
Classifier: Intended Audience :: Developers
Classifier: License :: OSI Approved :: MIT License
Classifier: Operating System :: OS Independent
Classifier: Programming Language :: Python :: 3
Classifier: Topic :: Documentation
Classifier: Topic :: Text Processing
Classifier: Topic :: Utilities
Provides-Extra: yaml
Requires-Dist: sphinx (>=2.4)
Provides-Extra: yaml
Requires-Dist: ruamel.yaml; extra == 'yaml'
